vl53l5cx/__init__.py
vl53l5cx/api.py
vl53l5cx/buffers.py
vl53l5cx/vl53l5cx.py
VL53L5CX-1.0.0.dist-info/LICENSE
VL53L5CX-1.0.0.dist-info/METADATA
VL53L5CX-1.0.0.dist-info/WHEEL
VL53L5CX-1.0.0.dist-info/top_level.txt
VL53L5CX-1.0.0.dist-info/RECORD
