Metadata-Version: 2.1
Name: VL53L5CX
Version: 1.0.0
Summary: Python native implementation of VL53L5CX ultra light driver code
Home-page: https://github.com/Abstract-Horizon/vl53l5cx_python
Author: Daniel Sendula
License: UNKNOWN
Platform: UNKNOWN
Classifier: Programming Language :: Python :: 3
Classifier: License :: OSI Approved :: Apache Software License
Classifier: Operating System :: OS Independent
Requires-Python: >=3.6
License-File: LICENSE
